setup.cfg
setup.py
django_remix.egg-info/PKG-INFO
django_remix.egg-info/SOURCES.txt
django_remix.egg-info/dependency_links.txt
django_remix.egg-info/requires.txt
django_remix.egg-info/top_level.txt
remix/__init__.py
remix/admin.py
remix/context_processors.py
remix/models.py
remix/urls.py
remix/views.py