Metadata-Version: 1.0
Name: django-remix
Version: 0.1.1
Summary: automatic-content selection via URLs
Home-page: http://code.google.com/p/django-remix/
Author: Secured Sciences Group
Author-email: labs@securedsciences.com
License: BSD
Keywords: django internet web content
Platform: UNKNOWN
Classifier: Programming Language :: Python
Classifier: License :: OSI Approved :: BSD License
Classifier: Intended Audience :: Developers
Classifier: Topic :: Internet
Classifier: Framework :: Django
